sane.py
tests/__init__.py
tests/sane.py
tests/test_catch_cyclic.py
tests/test_catch_cyclic_with_hooks.py
tests/test_catch_unknown.py
tests/test_cli.py
tests/test_concurrent.py
tests/test_conditions.py
tests/test_dependencies.py
tests/test_file_condition.py
tests/test_list.py
tests/test_no_ansi.py
tests/test_single_recipe.py
sane_build-7.3.dist-info/LICENSE.txt
sane_build-7.3.dist-info/METADATA
sane_build-7.3.dist-info/WHEEL
sane_build-7.3.dist-info/top_level.txt
sane_build-7.3.dist-info/RECORD
