Metadata-Version: 2.1
Name: sane-build
Version: 7.3
Summary: Make, but Sane
Home-page: https://github.com/mikeevmm/sane
Author: Miguel Murça
Author-email: miguel.murca+pypi@gmail.com
License: MIT
Keywords: make makefiles cmd utility cli
Platform: UNKNOWN
Classifier: Programming Language :: Python :: 3
Classifier: License :: OSI Approved :: MIT License
Classifier: Operating System :: POSIX
Requires-Python: >=3.6
